admk/__init__.py
admk/__main__.py
admk/admk_graph.py
admk/cli.py
admk/linear_solvers.py
admk-0.1.1.dist-info/AUTHORS.rst
admk-0.1.1.dist-info/LICENSE
admk-0.1.1.dist-info/METADATA
admk-0.1.1.dist-info/WHEEL
admk-0.1.1.dist-info/entry_points.txt
admk-0.1.1.dist-info/top_level.txt
admk-0.1.1.dist-info/RECORD
