Metadata-Version: 2.1
Name: admk
Version: 0.1.1
Summary: Algebraic Dynamics Monge Kantorovich solver for Basis Pursuit problem
Home-page: https://github.com/enricofacca/admk
Author: Enrico Facca
Author-email: enrico.facca@gmail.com
License: MIT
Project-URL: Documentation, https://admk.readthedocs.io/
Project-URL: Changelog, https://admk.readthedocs.io/en/latest/changelog.html
Project-URL: Issue Tracker, https://github.com/enricofacca/admk/issues
Platform: UNKNOWN
Classifier: Development Status :: 5 - Production/Stable
Classifier: Intended Audience :: Developers
Classifier: License :: OSI Approved :: MIT License
Classifier: Operating System :: Unix
Classifier: Operating System :: POSIX
Classifier: Operating System :: Microsoft :: Windows
Classifier: Programming Language :: Python
Classifier: Programming Language :: Python :: 3
Classifier: Programming Language :: Python :: 3 :: Only
Classifier: Programming Language :: Python :: 3.6
Classifier: Programming Language :: Python :: 3.7
Classifier: Programming Language :: Python :: 3.8
Classifier: Programming Language :: Python :: 3.9
Classifier: Programming Language :: Python :: 3.10
Classifier: Programming Language :: Python :: Implementation :: CPython
Classifier: Programming Language :: Python :: Implementation :: PyPy
Classifier: Topic :: Utilities
Requires-Python: >=3.6
Requires-Dist: rcis (>=0.2.0)
Requires-Dist: numpy (>=1.19.0)
Requires-Dist: scipy (>=1.5.0)
